cutex/__init__.py
cutex/inline_exec.py
cutex/src_module.py
cutex/utils.py
cutex/include/PyCUDATensorAccessor.cuh
cutex-0.3.9.dist-info/LICENSE
cutex-0.3.9.dist-info/METADATA
cutex-0.3.9.dist-info/WHEEL
cutex-0.3.9.dist-info/top_level.txt
cutex-0.3.9.dist-info/RECORD
