Metadata-Version: 2.1
Name: cutex
Version: 0.3.9
Summary: PyCUDA based PyTorch Extension Made Easy
Home-page: https://github.com/tjyuyao/cutex
Author: Yuyao Huang
Author-email: huangyuyao@outlook.com
Project-URL: Bug Tracker, https://github.com/tjyuyao/cutex/issues
Classifier: Programming Language :: Python :: 3
Classifier: License :: OSI Approved :: MIT License
Classifier: Operating System :: OS Independent
Requires-Python: >=3.6
License-File: LICENSE
Requires-Dist: pycuda
Requires-Dist: robotpy-cppheaderparser
